hungry_hungry_hippos.py
hungry_hungry_hippos-1.0.dist-info/METADATA
hungry_hungry_hippos-1.0.dist-info/WHEEL
hungry_hungry_hippos-1.0.dist-info/top_level.txt
hungry_hungry_hippos-1.0.dist-info/RECORD
