Metadata-Version: 2.1
Name: hungry-hungry-hippos
Version: 1.0
Summary: A python implementation of redlock, with examples
Home-page: https://github.com/krezreb/hungryhungryhippos
Author: krezreb
Author-email: josephbeeson@gmail.com
License: MIT
Platform: UNKNOWN
Requires-Dist: redis
